nuc_data_tool/__init__.py
nuc_data_tool/__main__.py
nuc_data_tool/config.toml
nuc_data_tool/anomaly_detection/__init__.py
nuc_data_tool/anomaly_detection/train_and_detection.py
nuc_data_tool/db/__init__.py
nuc_data_tool/db/base.py
nuc_data_tool/db/db_model.py
nuc_data_tool/db/db_utils.py
nuc_data_tool/db/fetch_data.py
nuc_data_tool/utils/__init__.py
nuc_data_tool/utils/configlib.py
nuc_data_tool/utils/data_extraction.py
nuc_data_tool/utils/fill_db.py
nuc_data_tool/utils/formatter.py
nuc_data_tool/utils/input_xml_file.py
nuc_data_tool/utils/middle_steps.py
nuc_data_tool/utils/middle_steps_pb2.py
nuc_data_tool/utils/relative_error_calculation.py
nuc_data_tool/utils/workbook.py
nuc_data_tool-4.1.0.dist-info/LICENSE
nuc_data_tool-4.1.0.dist-info/METADATA
nuc_data_tool-4.1.0.dist-info/WHEEL
nuc_data_tool-4.1.0.dist-info/entry_points.txt
nuc_data_tool-4.1.0.dist-info/top_level.txt
nuc_data_tool-4.1.0.dist-info/RECORD
