Metadata-Version: 2.1
Name: nuc-data-tool
Version: 4.1.0
Summary: an automated processing tool for specific nuclear data
Home-page: https://github.com/bookyue/nuclear_data_automated_processing
Author: Kyle Yue
Author-email: sevenbookyue@gmail.com
License: LGPL
Platform: UNKNOWN
Classifier: Development Status :: 2 - Pre-Alpha
Classifier: License :: OSI Approved :: GNU Lesser General Public License v2 or later (LGPLv2+)
Classifier: Programming Language :: Python
Classifier: Programming Language :: Python :: 3.8
Requires-Python: >=3.8
License-File: LICENSE
Requires-Dist: SQLAlchemy (>=1.4.0)
Requires-Dist: pandas
Requires-Dist: toml
Requires-Dist: protobuf
Requires-Dist: openpyxl
Requires-Dist: click
Requires-Dist: psycopg2
Requires-Dist: mysql-connector-python
Requires-Dist: pycaret (>=2.3.0)
